MANIFEST.in
README.rst
setup.py
YURL.egg-info/PKG-INFO
YURL.egg-info/SOURCES.txt
YURL.egg-info/dependency_links.txt
YURL.egg-info/top_level.txt
yurl/__init__.py
yurl/utils.py