Metadata-Version: 1.0
Name: YURL
Version: 0.11
Summary: Yurl is alternative url manipulation library
Home-page: http://github.com/homm/yurl/
Author: Aleksadr Karpinsky
Author-email: homm86@gmail.com
License: UNKNOWN
Platform: UNKNOWN
